bozepy/__init__.py
bozepy/alignment.py
bozepy/ccdproc.py
bozepy/phot.py
bozepy/spec.py
bozepy/utils.py
bozepy/data/bpm.fits.gz
bozepy/data/gaiadr3_gmag9.fits.gz
bozepy/data/master_dark.fits.gz
bozepy/data/master_flat-green.fits.gz
bozepy/data/master_zero.fits.gz
bozepy/data/sbig_wcs.fits
bozepy-1.0.16.dist-info/licenses/LICENSE
bozepy-1.0.16.dist-info/METADATA
bozepy-1.0.16.dist-info/WHEEL
bozepy-1.0.16.dist-info/top_level.txt
bozepy-1.0.16.dist-info/RECORD
