Metadata-Version: 2.4
Name: bozepy
Version: 1.0.16
Summary: Software to help running the MSU telescope and instruments
Home-page: https://github.com/dnidever/bozepy
Author: David Nidever
Author-email: David Nidever <dnidever@montana.edu>
Maintainer-email: David Nidever <dnidever@montana.edu>
License: MIT License
Project-URL: Documentation, https://bozepy.readthedocs.org
Project-URL: Repository, https://github.com/dnidever/bozepy
Keywords: observatory,imaging,spectroscopy
Classifier: Development Status :: 3 - Alpha
Classifier: License :: OSI Approved :: MIT License
Classifier: Programming Language :: Python
Requires: numpy
Requires: astropy
Requires: dlnpyutils
Requires: photutils
Requires-Python: >=3.9
License-File: LICENSE
Requires-Dist: scipy
Requires-Dist: numpy
Requires-Dist: matplotlib
Requires-Dist: astropy
Requires-Dist: dill
Requires-Dist: dlnpyutils
Requires-Dist: photutils
Requires-Dist: gdown
Provides-Extra: gui
Requires-Dist: PyQt5; extra == "gui"
Provides-Extra: cli
Requires-Dist: rich; extra == "cli"
Requires-Dist: click; extra == "cli"
Dynamic: author
Dynamic: home-page
Dynamic: license-file
Dynamic: requires
